core/__init__.py
core/arg_registry.py
core/imports.py
core/logging.py
core/plugin_monitor.py
core/reporter.py
core/signal_handler.py
main.py
scanners/__init__.py
scanners/extensions/__init__.py
scanners/extensions/brute_ftp_hydra.py
scanners/extensions/brute_http_wpscan.py
scanners/extensions/brute_kerbrute_password.py
scanners/extensions/brute_kerbrute_userenum.py
scanners/extensions/brute_mysql_hydra.py
scanners/extensions/brute_rdp_patator.py
scanners/extensions/brute_smb_hydra.py
scanners/extensions/brute_smtp_userenum.py
scanners/extensions/brute_ssh_hydra.py
scanners/extensions/brute_winrm_patator.py
scanners/extensions/built_in_args.py
scanners/extensions/enum_dns_dig.py
scanners/extensions/enum_ftp_gather.py
scanners/extensions/enum_generic_product_search.py
scanners/extensions/enum_http_curl_confirmation.py
scanners/extensions/enum_http_feroxbuster.py
scanners/extensions/enum_http_png_gowitness.py
scanners/extensions/enum_http_whatweb.py
scanners/extensions/enum_http_wpscan.py
scanners/extensions/enum_ldap_get_user_desc.py
scanners/extensions/enum_rpc_rpcclient.py
scanners/extensions/enum_smb_get_shares.py
scanners/extensions/enum_smb_nmap.py
scanners/extensions/enum_snmp_onesixtyone.py
scanners/extensions/enum_snmp_snmpwalk.py
scanners/extensions/scan_tcp_scanner.py
scanners/extensions/scan_udp_scanner.py
scanners/nmap_parser.py
scanners/scanner.py
templates/__init__.py
templates/default.html
scalable_plug_and_play_auto_detection_engine-1.0.0.dist-info/LICENSE
scalable_plug_and_play_auto_detection_engine-1.0.0.dist-info/METADATA
scalable_plug_and_play_auto_detection_engine-1.0.0.dist-info/WHEEL
scalable_plug_and_play_auto_detection_engine-1.0.0.dist-info/entry_points.txt
scalable_plug_and_play_auto_detection_engine-1.0.0.dist-info/RECORD
