Metadata-Version: 2.1
Name: scalable-plug-and-play-auto-detection-engine
Version: 1.0.0
Summary: SPADE is a modular vulnerability scanning framework that leverages external tools like nmap, curl, and more. It uses Python class decorators and reflection to auto-register modules for execution, making it easy to extend and customize.
License: AGPL 3.0
Author: ReKon64
Author-email: cookiewithoutraisins@gmail.com
Requires-Python: >=3.9,<4.0
Classifier: License :: Other/Proprietary License
Classifier: Programming Language :: Python :: 3
Classifier: Programming Language :: Python :: 3.9
Classifier: Programming Language :: Python :: 3.10
Classifier: Programming Language :: Python :: 3.11
Classifier: Programming Language :: Python :: 3.12
Classifier: Programming Language :: Python :: 3.13
Requires-Dist: beautifulsoup4 (>=4.13.4,<5.0.0)
Requires-Dist: jinja2 (>=3.1.5,<4.0.0)
Requires-Dist: psutil (>=5.9.8,<6.0.0)
Requires-Dist: requests (>=2.32.3,<3.0.0)
